<?xml version="1.0" encoding="utf-8"?><root><item><ID>1</ID><UserIP>192.168.0.128</UserIP><CDate>Thu Jun 23 20:00:11 UTC+0800 2011</CDate><CDateInt>1308830411</CDateInt><BarID>2011142943876548318</BarID></item><item><ID>2</ID><UserIP>192.168.0.128</UserIP><CDate>Thu Jun 23 20:00:24 UTC+0800 2011</CDate><CDateInt>1308830424</CDateInt><BarID>2011142943876548318</BarID></item><item><ID>3</ID><UserIP>192.168.0.128</UserIP><CDate>Thu Jun 23 20:00:31 UTC+0800 2011</CDate><CDateInt>1308830431</CDateInt><BarID>2011142943876548318</BarID></item><item><ID>4</ID><UserIP>192.168.0.128</UserIP><CDate>Thu Jun 23 20:00:47 UTC+0800 2011</CDate><CDateInt>1308830447</CDateInt><BarID>2011142943876548318</BarID></item><item><ID>5</ID><UserIP>192.168.0.128</UserIP><CDate>Thu Jun 23 20:02:01 UTC+0800 2011</CDate><CDateInt>1308830521</CDateInt><BarID>2011142943876548318</BarID></item><item><ID>6</ID><UserIP>192.168.0.32</UserIP><CDate>Thu Jun 23 21:22:59 UTC+0800 2011</CDate><CDateInt>1308835379</CDateInt><BarID>2011142943876548318</BarID></item><item><ID>7</ID><UserIP>192.168.0.32</UserIP><CDate>Thu Jun 23 21:27:49 UTC+0800 2011</CDate><CDateInt>1308835669</CDateInt><BarID>2011142943876548318</BarID></item></root>