<?xml version="1.0" encoding="utf-8"?><root><item><ID>1</ID><UserIP>192.168.0.235</UserIP><CDate>Thu Jun 23 06:13:59 UTC+0800 2011</CDate><CDateInt>1308780839</CDateInt><BarID>gzhaitongwangba</BarID></item><item><ID>2</ID><UserIP>192.168.0.173</UserIP><CDate>Thu Jun 23 08:57:18 UTC+0800 2011</CDate><CDateInt>1308790638</CDateInt><BarID>gzhaitongwangba</BarID></item><item><ID>3</ID><UserIP>192.168.1.93</UserIP><CDate>Thu Jun 23 08:59:03 UTC+0800 2011</CDate><CDateInt>1308790743</CDateInt><BarID>gzhaitongwangba</BarID></item><item><ID>4</ID><UserIP>192.168.0.117</UserIP><CDate>Thu Jun 23 15:16:22 UTC+0800 2011</CDate><CDateInt>1308813382</CDateInt><BarID>gzhaitongwangba</BarID></item><item><ID>5</ID><UserIP>192.168.1.200</UserIP><CDate>Thu Jun 23 17:57:11 UTC+0800 2011</CDate><CDateInt>1308823031</CDateInt><BarID>gzhaitongwangba</BarID></item><item><ID>6</ID><UserIP>192.168.1.241</UserIP><CDate>Thu Jun 23 18:06:14 UTC+0800 2011</CDate><CDateInt>1308823574</CDateInt><BarID>gzhaitongwangba</BarID></item><item><ID>7</ID><UserIP>192.168.1.85</UserIP><CDate>Thu Jun 23 23:45:48 UTC+0800 2011</CDate><CDateInt>1308843948</CDateInt><BarID>gzhaitongwangba</BarID></item></root>