<?xml version="1.0" encoding="utf-8"?><root><info BarID="15920943808727201026" /><item><UserIP>192.168.0.138</UserIP><CDate>Thu Jun 23 03:10:42 UTC+0800 2011</CDate><CDateInt>1308769842</CDateInt></item><item><UserIP>192.168.0.94</UserIP><CDate>Thu Jun 23 03:21:16 UTC+0800 2011</CDate><CDateInt>1308770476</CDateInt></item><item><UserIP>192.168.0.94</UserIP><CDate>Thu Jun 23 03:21:56 UTC+0800 2011</CDate><CDateInt>1308770516</CDateInt></item><item><UserIP>192.168.0.94</UserIP><CDate>Thu Jun 23 03:22:04 UTC+0800 2011</CDate><CDateInt>1308770524</CDateInt></item><item><UserIP>192.168.0.94</UserIP><CDate>Thu Jun 23 03:22:19 UTC+0800 2011</CDate><CDateInt>1308770539</CDateInt></item><item><UserIP>192.168.0.94</UserIP><CDate>Thu Jun 23 03:27:30 UTC+0800 2011</CDate><CDateInt>1308770850</CDateInt></item><item><UserIP>192.168.0.94</UserIP><CDate>Thu Jun 23 04:37:21 UTC+0800 2011</CDate><CDateInt>1308775041</CDateInt></item><item><UserIP>192.168.0.94</UserIP><CDate>Thu Jun 23 04:37:46 UTC+0800 2011</CDate><CDateInt>1308775066</CDateInt></item><item><UserIP>192.168.0.94</UserIP><CDate>Thu Jun 23 04:38:04 UTC+0800 2011</CDate><CDateInt>1308775084</CDateInt></item><item><UserIP>192.168.0.94</UserIP><CDate>Thu Jun 23 04:38:20 UTC+0800 2011</CDate><CDateInt>1308775100</CDateInt></item><item><UserIP>192.168.0.94</UserIP><CDate>Thu Jun 23 04:38:42 UTC+0800 2011</CDate><CDateInt>1308775122</CDateInt></item><item><UserIP>192.168.0.94</UserIP><CDate>Thu Jun 23 04:38:54 UTC+0800 2011</CDate><CDateInt>1308775134</CDateInt></item><item><UserIP>192.168.0.94</UserIP><CDate>Thu Jun 23 04:39:14 UTC+0800 2011</CDate><CDateInt>1308775154</CDateInt></item><item><UserIP>192.168.0.94</UserIP><CDate>Thu Jun 23 04:39:39 UTC+0800 2011</CDate><CDateInt>1308775179</CDateInt></item><item><UserIP>192.168.0.48</UserIP><CDate>Thu Jun 23 04:57:30 UTC+0800 2011</CDate><CDateInt>1308776250</CDateInt></item><item><UserIP>192.168.0.94</UserIP><CDate>Thu Jun 23 05:06:21 UTC+0800 2011</CDate><CDateInt>1308776781</CDateInt></item><item><UserIP>192.168.0.48</UserIP><CDate>Thu Jun 23 05:26:40 UTC+0800 2011</CDate><CDateInt>1308778000</CDateInt></item><item><UserIP>192.168.0.94</UserIP><CDate>Thu Jun 23 05:50:08 UTC+0800 2011</CDate><CDateInt>1308779408</CDateInt></item><item><UserIP>192.168.0.94</UserIP><CDate>Thu Jun 23 05:50:22 UTC+0800 2011</CDate><CDateInt>1308779422</CDateInt></item><item><UserIP>192.168.0.94</UserIP><CDate>Thu Jun 23 05:51:11 UTC+0800 2011</CDate><CDateInt>1308779471</CDateInt></item><item><UserIP>192.168.0.94</UserIP><CDate>Thu Jun 23 05:51:23 UTC+0800 2011</CDate><CDateInt>1308779483</CDateInt></item><item><UserIP>192.168.0.94</UserIP><CDate>Thu Jun 23 05:53:21 UTC+0800 2011</CDate><CDateInt>1308779601</CDateInt></item><item><UserIP>192.168.0.94</UserIP><CDate>Thu Jun 23 05:53:33 UTC+0800 2011</CDate><CDateInt>1308779613</CDateInt></item><item><UserIP>192.168.0.94</UserIP><CDate>Thu Jun 23 05:54:53 UTC+0800 2011</CDate><CDateInt>1308779693</CDateInt></item><item><UserIP>192.168.0.94</UserIP><CDate>Thu Jun 23 05:55:08 UTC+0800 2011</CDate><CDateInt>1308779708</CDateInt></item><item><UserIP>192.168.0.94</UserIP><CDate>Thu Jun 23 06:06:04 UTC+0800 2011</CDate><CDateInt>1308780364</CDateInt></item><item><UserIP>192.168.0.30</UserIP><CDate>Thu Jun 23 09:08:28 UTC+0800 2011</CDate><CDateInt>1308791308</CDateInt></item><item><UserIP>192.168.0.172</UserIP><CDate>Thu Jun 23 09:25:40 UTC+0800 2011</CDate><CDateInt>1308792340</CDateInt></item><item><UserIP>192.168.0.172</UserIP><CDate>Thu Jun 23 09:27:08 UTC+0800 2011</CDate><CDateInt>1308792428</CDateInt></item><item><UserIP>192.168.0.172</UserIP><CDate>Thu Jun 23 09:27:12 UTC+0800 2011</CDate><CDateInt>1308792432</CDateInt></item><item><UserIP>192.168.0.172</UserIP><CDate>Thu Jun 23 09:27:14 UTC+0800 2011</CDate><CDateInt>1308792434</CDateInt></item><item><UserIP>192.168.0.172</UserIP><CDate>Thu Jun 23 09:27:15 UTC+0800 2011</CDate><CDateInt>1308792435</CDateInt></item><item><UserIP>192.168.0.62</UserIP><CDate>Thu Jun 23 11:47:15 UTC+0800 2011</CDate><CDateInt>1308800835</CDateInt></item><item><UserIP>192.168.0.141</UserIP><CDate>Thu Jun 23 13:52:02 UTC+0800 2011</CDate><CDateInt>1308808322</CDateInt></item><item><UserIP>192.168.0.48</UserIP><CDate>Thu Jun 23 19:18:35 UTC+0800 2011</CDate><CDateInt>1308827915</CDateInt></item><item><UserIP>192.168.0.36</UserIP><CDate>Thu Jun 23 22:02:51 UTC+0800 2011</CDate><CDateInt>1308837771</CDateInt></item><item><UserIP>192.168.0.32</UserIP><CDate>Thu Jun 23 22:45:32 UTC+0800 2011</CDate><CDateInt>1308840332</CDateInt></item></root>