<?xml version="1.0" encoding="utf-8"?><root><item><ID>1</ID><UserIP>60.195.39.98</UserIP><CDate>Wed Jun 22 23:46:36 UTC+0800 2011</CDate><CDateInt>1308757596</CDateInt><BarID>201730713201069157311</BarID></item><item><ID>2</ID><UserIP>60.195.39.98</UserIP><CDate>Wed Jun 22 23:47:19 UTC+0800 2011</CDate><CDateInt>1308757639</CDateInt><BarID>201730713201069157311</BarID></item><item><ID>3</ID><UserIP>60.195.39.98</UserIP><CDate>Thu Jun 23 02:57:25 UTC+0800 2011</CDate><CDateInt>1308769045</CDateInt><BarID>201730713201069157311</BarID></item><item><ID>4</ID><UserIP>60.195.39.98</UserIP><CDate>Thu Jun 23 02:58:32 UTC+0800 2011</CDate><CDateInt>1308769112</CDateInt><BarID>201730713201069157311</BarID></item><item><ID>5</ID><UserIP>60.195.39.98</UserIP><CDate>Thu Jun 23 03:01:01 UTC+0800 2011</CDate><CDateInt>1308769261</CDateInt><BarID>201730713201069157311</BarID></item><item><ID>6</ID><UserIP>60.195.39.55</UserIP><CDate>Thu Jun 23 08:31:08 UTC+0800 2011</CDate><CDateInt>1308789068</CDateInt><BarID>201730713201069157311</BarID></item><item><ID>7</ID><UserIP>60.195.39.84</UserIP><CDate>Thu Jun 23 09:23:37 UTC+0800 2011</CDate><CDateInt>1308792217</CDateInt><BarID>201730713201069157311</BarID></item><item><ID>8</ID><UserIP>60.195.39.46</UserIP><CDate>Thu Jun 23 15:11:50 UTC+0800 2011</CDate><CDateInt>1308813110</CDateInt><BarID>201730713201069157311</BarID></item><item><ID>9</ID><UserIP>60.195.39.46</UserIP><CDate>Thu Jun 23 15:11:50 UTC+0800 2011</CDate><CDateInt>1308813110</CDateInt><BarID>201730713201069157311</BarID></item></root>