<?xml version="1.0" encoding="utf-8"?><root><info BarID="488103011311620101510" /><item><UserIP>192.168.0.46</UserIP><CDate>Thu Jun 23 18:52:16 UTC+0800 2011</CDate><CDateInt>1308826336</CDateInt></item><item><UserIP>192.168.0.11</UserIP><CDate>Thu Jun 23 18:52:37 UTC+0800 2011</CDate><CDateInt>1308826357</CDateInt></item><item><UserIP>192.168.0.46</UserIP><CDate>Thu Jun 23 18:52:38 UTC+0800 2011</CDate><CDateInt>1308826358</CDateInt></item><item><UserIP>192.168.0.46</UserIP><CDate>Thu Jun 23 18:56:57 UTC+0800 2011</CDate><CDateInt>1308826617</CDateInt></item><item><UserIP>192.168.0.35</UserIP><CDate>Thu Jun 23 23:06:40 UTC+0800 2011</CDate><CDateInt>1308841600</CDateInt></item><item><UserIP>192.168.0.35</UserIP><CDate>Thu Jun 23 23:08:41 UTC+0800 2011</CDate><CDateInt>1308841721</CDateInt></item><item><UserIP>192.168.0.35</UserIP><CDate>Thu Jun 23 23:09:23 UTC+0800 2011</CDate><CDateInt>1308841763</CDateInt></item><item><UserIP>192.168.0.35</UserIP><CDate>Thu Jun 23 23:10:37 UTC+0800 2011</CDate><CDateInt>1308841837</CDateInt></item><item><UserIP>192.168.0.49</UserIP><CDate>Thu Jun 23 23:25:27 UTC+0800 2011</CDate><CDateInt>1308842727</CDateInt></item><item><UserIP>192.168.0.49</UserIP><CDate>Thu Jun 23 23:25:43 UTC+0800 2011</CDate><CDateInt>1308842743</CDateInt></item><item><UserIP>192.168.0.35</UserIP><CDate>Thu Jun 23 23:33:30 UTC+0800 2011</CDate><CDateInt>1308843210</CDateInt></item><item><UserIP>192.168.0.2</UserIP><CDate>Thu Jun 23 23:53:58 UTC+0800 2011</CDate><CDateInt>1308844438</CDateInt></item></root>