<?xml version="1.0" encoding="utf-8"?><root><info BarID="95495433722011111435" /><item><UserIP>192.168.0.179</UserIP><CDate>Thu Jun 23 07:34:50 UTC+0800 2011</CDate><CDateInt>1308785690</CDateInt></item><item><UserIP>192.168.0.178</UserIP><CDate>Thu Jun 23 13:20:22 UTC+0800 2011</CDate><CDateInt>1308806422</CDateInt></item><item><UserIP>192.168.0.178</UserIP><CDate>Thu Jun 23 13:23:20 UTC+0800 2011</CDate><CDateInt>1308806600</CDateInt></item><item><UserIP>192.168.0.178</UserIP><CDate>Thu Jun 23 13:23:35 UTC+0800 2011</CDate><CDateInt>1308806615</CDateInt></item><item><UserIP>192.168.0.178</UserIP><CDate>Thu Jun 23 13:25:15 UTC+0800 2011</CDate><CDateInt>1308806715</CDateInt></item><item><UserIP>192.168.0.178</UserIP><CDate>Thu Jun 23 13:25:56 UTC+0800 2011</CDate><CDateInt>1308806756</CDateInt></item></root>