<?xml version="1.0" encoding="utf-8"?><root><info BarID="zhongqinliehuod" /><item><UserIP>192.168.0.69</UserIP><CDate>Thu Jun 23 04:28:37 UTC+0800 2011</CDate><CDateInt>1308774517</CDateInt></item><item><UserIP>192.168.0.21</UserIP><CDate>Thu Jun 23 05:29:47 UTC+0800 2011</CDate><CDateInt>1308778187</CDateInt></item><item><UserIP>192.168.0.101</UserIP><CDate>Thu Jun 23 05:30:15 UTC+0800 2011</CDate><CDateInt>1308778215</CDateInt></item><item><UserIP>192.168.0.69</UserIP><CDate>Thu Jun 23 05:46:01 UTC+0800 2011</CDate><CDateInt>1308779161</CDateInt></item><item><UserIP>192.168.0.20</UserIP><CDate>Thu Jun 23 05:57:10 UTC+0800 2011</CDate><CDateInt>1308779830</CDateInt></item><item><UserIP>192.168.0.76</UserIP><CDate>Thu Jun 23 07:54:59 UTC+0800 2011</CDate><CDateInt>1308786899</CDateInt></item><item><UserIP>192.168.0.94</UserIP><CDate>Thu Jun 23 08:43:46 UTC+0800 2011</CDate><CDateInt>1308789826</CDateInt></item><item><UserIP>192.168.0.94</UserIP><CDate>Thu Jun 23 08:44:19 UTC+0800 2011</CDate><CDateInt>1308789859</CDateInt></item><item><UserIP>192.168.0.42</UserIP><CDate>Thu Jun 23 08:47:42 UTC+0800 2011</CDate><CDateInt>1308790062</CDateInt></item><item><UserIP>192.168.0.13</UserIP><CDate>Thu Jun 23 09:04:21 UTC+0800 2011</CDate><CDateInt>1308791061</CDateInt></item><item><UserIP>192.168.0.89</UserIP><CDate>Thu Jun 23 09:15:27 UTC+0800 2011</CDate><CDateInt>1308791727</CDateInt></item><item><UserIP>192.168.0.8</UserIP><CDate>Thu Jun 23 10:50:05 UTC+0800 2011</CDate><CDateInt>1308797405</CDateInt></item><item><UserIP>192.168.0.8</UserIP><CDate>Thu Jun 23 10:52:29 UTC+0800 2011</CDate><CDateInt>1308797549</CDateInt></item><item><UserIP>192.168.0.94</UserIP><CDate>Thu Jun 23 10:54:12 UTC+0800 2011</CDate><CDateInt>1308797652</CDateInt></item><item><UserIP>192.168.0.248</UserIP><CDate>Thu Jun 23 11:20:42 UTC+0800 2011</CDate><CDateInt>1308799242</CDateInt></item><item><UserIP>192.168.0.24</UserIP><CDate>Thu Jun 23 11:36:45 UTC+0800 2011</CDate><CDateInt>1308800205</CDateInt></item><item><UserIP>192.168.0.110</UserIP><CDate>Thu Jun 23 11:41:40 UTC+0800 2011</CDate><CDateInt>1308800500</CDateInt></item><item><UserIP>192.168.0.110</UserIP><CDate>Thu Jun 23 11:46:02 UTC+0800 2011</CDate><CDateInt>1308800762</CDateInt></item><item><UserIP>192.168.0.84</UserIP><CDate>Thu Jun 23 12:12:46 UTC+0800 2011</CDate><CDateInt>1308802366</CDateInt></item><item><UserIP>192.168.0.84</UserIP><CDate>Thu Jun 23 12:14:18 UTC+0800 2011</CDate><CDateInt>1308802458</CDateInt></item><item><UserIP>192.168.0.84</UserIP><CDate>Thu Jun 23 12:16:41 UTC+0800 2011</CDate><CDateInt>1308802601</CDateInt></item><item><UserIP>192.168.0.7</UserIP><CDate>Thu Jun 23 13:29:43 UTC+0800 2011</CDate><CDateInt>1308806983</CDateInt></item><item><UserIP>192.168.0.248</UserIP><CDate>Thu Jun 23 13:32:17 UTC+0800 2011</CDate><CDateInt>1308807137</CDateInt></item><item><UserIP>192.168.0.248</UserIP><CDate>Thu Jun 23 13:32:27 UTC+0800 2011</CDate><CDateInt>1308807147</CDateInt></item><item><UserIP>192.168.0.248</UserIP><CDate>Thu Jun 23 13:35:21 UTC+0800 2011</CDate><CDateInt>1308807321</CDateInt></item><item><UserIP>192.168.0.2</UserIP><CDate>Thu Jun 23 18:14:27 UTC+0800 2011</CDate><CDateInt>1308824067</CDateInt></item><item><UserIP>192.168.0.2</UserIP><CDate>Thu Jun 23 18:28:03 UTC+0800 2011</CDate><CDateInt>1308824883</CDateInt></item><item><UserIP>192.168.0.20</UserIP><CDate>Thu Jun 23 18:36:43 UTC+0800 2011</CDate><CDateInt>1308825403</CDateInt></item><item><UserIP>192.168.0.109</UserIP><CDate>Thu Jun 23 19:15:12 UTC+0800 2011</CDate><CDateInt>1308827712</CDateInt></item><item><UserIP>192.168.0.61</UserIP><CDate>Thu Jun 23 19:56:53 UTC+0800 2011</CDate><CDateInt>1308830213</CDateInt></item><item><UserIP>192.168.0.57</UserIP><CDate>Thu Jun 23 20:05:23 UTC+0800 2011</CDate><CDateInt>1308830723</CDateInt></item><item><UserIP>192.168.0.57</UserIP><CDate>Thu Jun 23 20:06:22 UTC+0800 2011</CDate><CDateInt>1308830782</CDateInt></item><item><UserIP>192.168.0.57</UserIP><CDate>Thu Jun 23 20:06:30 UTC+0800 2011</CDate><CDateInt>1308830790</CDateInt></item><item><UserIP>192.168.0.57</UserIP><CDate>Thu Jun 23 20:06:48 UTC+0800 2011</CDate><CDateInt>1308830808</CDateInt></item><item><UserIP>192.168.0.57</UserIP><CDate>Thu Jun 23 20:07:01 UTC+0800 2011</CDate><CDateInt>1308830821</CDateInt></item><item><UserIP>192.168.0.57</UserIP><CDate>Thu Jun 23 20:07:38 UTC+0800 2011</CDate><CDateInt>1308830858</CDateInt></item><item><UserIP>192.168.0.57</UserIP><CDate>Thu Jun 23 20:07:56 UTC+0800 2011</CDate><CDateInt>1308830876</CDateInt></item><item><UserIP>192.168.0.47</UserIP><CDate>Thu Jun 23 21:41:42 UTC+0800 2011</CDate><CDateInt>1308836502</CDateInt></item><item><UserIP>192.168.0.47</UserIP><CDate>Thu Jun 23 21:43:34 UTC+0800 2011</CDate><CDateInt>1308836614</CDateInt></item><item><UserIP>192.168.0.68</UserIP><CDate>Thu Jun 23 22:22:53 UTC+0800 2011</CDate><CDateInt>1308838973</CDateInt></item><item><UserIP>192.168.0.35</UserIP><CDate>Thu Jun 23 22:24:11 UTC+0800 2011</CDate><CDateInt>1308839051</CDateInt></item><item><UserIP>192.168.0.35</UserIP><CDate>Thu Jun 23 22:24:46 UTC+0800 2011</CDate><CDateInt>1308839086</CDateInt></item><item><UserIP>192.168.0.35</UserIP><CDate>Thu Jun 23 22:27:36 UTC+0800 2011</CDate><CDateInt>1308839256</CDateInt></item><item><UserIP>192.168.0.35</UserIP><CDate>Thu Jun 23 22:28:03 UTC+0800 2011</CDate><CDateInt>1308839283</CDateInt></item><item><UserIP>192.168.0.103</UserIP><CDate>Thu Jun 23 23:56:00 UTC+0800 2011</CDate><CDateInt>1308844560</CDateInt></item></root>